kshort/__init__.py
kshort/config.py
kshort/main.py
kshort/project.py
kshort/projects.py
kshort/selector.py
kshort/utils.py
kshort-0.0.9.dist-info/METADATA
kshort-0.0.9.dist-info/WHEEL
kshort-0.0.9.dist-info/entry_points.txt
kshort-0.0.9.dist-info/top_level.txt
kshort-0.0.9.dist-info/RECORD
