Metadata-Version: 2.1
Name: kshort
Version: 0.0.9
Summary: Module to manage your projects using kitty and neovim
Home-page: https://github.com/McAlvaro/kshort
Author: McAlvaro
Author-email: mc.alvaro641@gmail.com
License: UNKNOWN
Keywords: python,kshort
Platform: UNKNOWN
Classifier: Programming Language :: Python :: 3
